PoorMansHeadless/LICENSE
PoorMansHeadless/README.MD
PoorMansHeadless/__init__.py
PoorMansHeadless/requirements.txt
PoorMansHeadless/thirdparty.json
PoorMansHeadless-0.10.dist-info/LICENSE.rst
PoorMansHeadless-0.10.dist-info/METADATA
PoorMansHeadless-0.10.dist-info/WHEEL
PoorMansHeadless-0.10.dist-info/top_level.txt
PoorMansHeadless-0.10.dist-info/RECORD
