Metadata-Version: 2.1
Name: PoorMansHeadless
Version: 0.10
Summary: Make a headless window out of every window! Perfect for undetected chromedriver (Selenium) to pass bot detection in headless mode.
Home-page: https://github.com/hansalemaos/PoorMansHeadless
Author: Johannes Fischer
Author-email: <aulasparticularesdealemaosp@gmail.com>
License: MIT
Keywords: headless,selenium,automation
Classifier: Development Status :: 4 - Beta
Classifier: Programming Language :: Python :: 3 :: Only
Classifier: Programming Language :: Python :: 3.9
Classifier: Topic :: Scientific/Engineering :: Visualization
Classifier: Topic :: Software Development :: Libraries :: Python Modules
Classifier: Topic :: Text Editors :: Text Processing
Classifier: Topic :: Text Processing :: General
Classifier: Topic :: Text Processing :: Indexing
Classifier: Topic :: Text Processing :: Filters
Classifier: Topic :: Utilities
License-File: LICENSE.rst
Requires-Dist: a-cv-imwrite-imread-plus
Requires-Dist: ctypes-screenshots
Requires-Dist: ctypes-window-info
Requires-Dist: kthread
Requires-Dist: opencv-python
Requires-Dist: pandas
